[
  {
    "slug": "welcome-prep",
    "photographer": "NaNa Photography",
    "photographer_url": "https://www.pexels.com/@thenanagang",
    "pexels_url": "https://www.pexels.com/photo/a-puppy-with-a-dog-collar-4438585/",
    "pexels_id": 4438585
  },
  {
    "slug": "first-dog-guide",
    "photographer": "柳树 无",
    "photographer_url": "https://www.pexels.com/@1116199243",
    "pexels_url": "https://www.pexels.com/photo/cute-puppy-held-in-arms-on-a-sunny-day-35342694/",
    "pexels_id": 35342694
  },
  {
    "slug": "first-cat-guide",
    "photographer": "Helena Jankovičová Kováčová",
    "photographer_url": "https://www.pexels.com/@helen1",
    "pexels_url": "https://www.pexels.com/photo/kitten-by-his-bed-in-apartment-20211113/",
    "pexels_id": 20211113
  },
  {
    "slug": "starter-set",
    "photographer": "MART  PRODUCTION",
    "photographer_url": "https://www.pexels.com/@mart-production",
    "pexels_url": "https://www.pexels.com/photo/stationery-items-lying-on-a-table-7718715/",
    "pexels_id": 7718715
  },
  {
    "slug": "journal-first-pet-checklist",
    "photographer": "RDNE Stock project",
    "photographer_url": "https://www.pexels.com/@rdne",
    "pexels_url": "https://www.pexels.com/photo/list-written-in-a-notepad-with-pen-8581014/",
    "pexels_id": 8581014
  },
  {
    "slug": "journal-first-pet-cost",
    "photographer": "Jahra Tasfia Reza",
    "photographer_url": "https://www.pexels.com/@jahratreza",
    "pexels_url": "https://www.pexels.com/photo/calculator-and-notebook-on-study-desk-36488453/",
    "pexels_id": 36488453
  },
  {
    "slug": "journal-pet-vaccine-schedule",
    "photographer": "Tima Miroshnichenko",
    "photographer_url": "https://www.pexels.com/@tima-miroshnichenko",
    "pexels_url": "https://www.pexels.com/photo/a-dog-at-the-clinic-6235650/",
    "pexels_id": 6235650
  },
  {
    "slug": "journal-dog-walk-when",
    "photographer": "Brett Aukburg",
    "photographer_url": "https://www.pexels.com/@brett-aukburg-2161021813",
    "pexels_url": "https://www.pexels.com/photo/adorable-shih-tzu-on-a-leash-walking-outdoors-37322677/",
    "pexels_id": 37322677
  },
  {
    "slug": "journal-cat-cage-necessary",
    "photographer": "Ayyeee Ayyeee",
    "photographer_url": "https://www.pexels.com/@ayyeee-ayyeee-434363205",
    "pexels_url": "https://www.pexels.com/photo/a-cat-sitting-in-a-cage-20049568/",
    "pexels_id": 20049568
  },
  {
    "slug": "journal-first-days",
    "photographer": "Tanya Gorelova",
    "photographer_url": "https://www.pexels.com/@tanya-gorelova-2199357",
    "pexels_url": "https://www.pexels.com/photo/a-cute-dog-sleeping-on-the-floor-3860313/",
    "pexels_id": 3860313
  },
  {
    "slug": "journal-home-safety",
    "photographer": "Helena Lopes",
    "photographer_url": "https://www.pexels.com/@helenalopes",
    "pexels_url": "https://www.pexels.com/photo/woman-cleaning-leaving-room-27176669/",
    "pexels_id": 27176669
  },
  {
    "slug": "journal-first-shopping",
    "photographer": "Maurício Mascaro",
    "photographer_url": "https://www.pexels.com/@maumascaro",
    "pexels_url": "https://www.pexels.com/photo/assorted-item-lot-796584/",
    "pexels_id": 796584
  },
  {
    "slug": "journal-dog-alone-training",
    "photographer": "HONG SON",
    "photographer_url": "https://www.pexels.com/@hson",
    "pexels_url": "https://www.pexels.com/photo/dog-sleeping-near-trash-on-street-4335585/",
    "pexels_id": 4335585
  },
  {
    "slug": "journal-cat-toilet-fixes",
    "photographer": "Natalia Sevruk",
    "photographer_url": "https://www.pexels.com/@natalia-sevruk-636238602",
    "pexels_url": "https://www.pexels.com/photo/adorable-calico-cat-in-a-cardboard-box-indoors-36279715/",
    "pexels_id": 36279715
  },
  {
    "slug": "journal-pet-fast-eating",
    "photographer": "MART  PRODUCTION",
    "photographer_url": "https://www.pexels.com/@mart-production",
    "pexels_url": "https://www.pexels.com/photo/brown-dog-eating-8434676/",
    "pexels_id": 8434676
  },
  {
    "slug": "journal-first-summer",
    "photographer": "Ayyeee Ayyeee",
    "photographer_url": "https://www.pexels.com/@ayyeee-ayyeee-434363205",
    "pexels_url": "https://www.pexels.com/photo/cozy-indoor-scene-with-a-dog-and-fish-tank-36802162/",
    "pexels_id": 36802162
  },
  {
    "slug": "journal-pet-bousai",
    "photographer": "Roger Brown",
    "photographer_url": "https://www.pexels.com/@roger-brown-3435524",
    "pexels_url": "https://www.pexels.com/photo/first-aid-kits-on-white-background-5149757/",
    "pexels_id": 5149757
  },
  {
    "slug": "journal-kanto-pet-outings",
    "photographer": "Huu Huynh",
    "photographer_url": "https://www.pexels.com/@imhh",
    "pexels_url": "https://www.pexels.com/photo/woman-walking-dog-on-promenade-in-yokohama-23024045/",
    "pexels_id": 23024045
  }
]